Metadata-Version: 2.1
Name: unusualwhales-python-client
Version: 4.2.3
Summary: A client library for accessing Unusual Whales API
Author: Mac Anderson
Author-email: mac@macanderson.com
Requires-Python: >=3.10.0,<4.0.0
Classifier: Programming Language :: Python :: 3
Classifier: Programming Language :: Python :: 3.10
Classifier: Programming Language :: Python :: 3.11
Classifier: Programming Language :: Python :: 3.12
Requires-Dist: attrs (>=21.3.0,<22.0.0)
Requires-Dist: httpx (>=0.20.0,<0.28.0)
Requires-Dist: python-dateutil (>=2.8.0,<3.0.0)
Requires-Dist: python-dotenv (>=0.21.0,<0.22.0)
